faculty/__init__.py
faculty/_oneofschema.py
faculty/config.py
faculty/context.py
faculty/clients/__init__.py
faculty/clients/account.py
faculty/clients/api.py
faculty/clients/auth.py
faculty/clients/base.py
faculty/clients/cluster.py
faculty/clients/environment.py
faculty/clients/experiment.py
faculty/clients/invitation.py
faculty/clients/job.py
faculty/clients/log.py
faculty/clients/model.py
faculty/clients/object.py
faculty/clients/project.py
faculty/clients/report.py
faculty/clients/secret.py
faculty/clients/server.py
faculty/clients/serveragent.py
faculty/clients/user.py
faculty/clients/workspace.py
faculty/datasets/__init__.py
faculty/datasets/transfer.py
faculty/datasets/util.py
faculty/session/__init__.py
faculty/session/accesstoken.py
faculty-0.31.0.dist-info/licenses/LICENSE-2.0.txt
tests/__init__.py
tests/test_config.py
tests/test_context.py
tests/test_init.py
tests/clients/__init__.py
tests/clients/test_account.py
tests/clients/test_auth.py
tests/clients/test_base.py
tests/clients/test_cluster.py
tests/clients/test_environment.py
tests/clients/test_init.py
tests/clients/test_invitation.py
tests/clients/test_job.py
tests/clients/test_log.py
tests/clients/test_model.py
tests/clients/test_object.py
tests/clients/test_project.py
tests/clients/test_report.py
tests/clients/test_secret.py
tests/clients/test_server.py
tests/clients/test_serveragent.py
tests/clients/test_user.py
tests/clients/test_workspace.py
tests/clients/experiment/__init__.py
tests/clients/experiment/test_client.py
tests/clients/experiment/test_schemas.py
tests/datasets/__init__.py
tests/datasets/test_init.py
tests/datasets/test_transfer.py
faculty-0.31.0.dist-info/METADATA
faculty-0.31.0.dist-info/WHEEL
faculty-0.31.0.dist-info/top_level.txt
faculty-0.31.0.dist-info/RECORD
